econt/__init__.py
econt/api.py
econt/helper_functions.py
econt/report_types.py
econt/request_types.py
econt/status_codes.py
econt_test-0.1.0.dist-info/METADATA
econt_test-0.1.0.dist-info/RECORD
econt_test-0.1.0.dist-info/WHEEL
econt_test-0.1.0.dist-info/top_level.txt
tests/__init__.py
tests/countries_tests.py
tests/create_shipment_tests.py
tests/credentials.py
tests/get_clients_tests.py
tests/get_delivery_days_tests.py
tests/get_post_tariff_tests.py
tests/get_postboxes_tests.py
tests/get_quarters_tests.py
tests/get_regions_tests.py
tests/get_streets_by_city_tests.py
tests/get_zones_tests.py
tests/offices_by_city_tests.py
tests/offices_tests.py
tests/quarters_by_post_code_tests.py
tests/request_tests.py
tests/retrieve_profile_tests.py
tests/retrieve_shipment_info_tests.py
tests/seller_addresses_tests.py
tests/validate_address_tests.py
tests/validate_cd_agreement_tests.py
tests/xml_builder_tests.py
