Metadata-Version: 2.1
Name: econt-test
Version: 0.1.0
Summary: Integrating Econt API using Python
Home-page: https://gitlab.melontech.com/melontech/econt.git
Author: Hakan Halil
Author-email: hhalil@melontech.com
License: UNKNOWN
Platform: UNKNOWN
Classifier: Development Status :: 4 - Beta
Classifier: Programming Language :: Python :: 2.7
Classifier: Programming Language :: Python :: 3.3
Classifier: Programming Language :: Python :: 3.5
Classifier: Programming Language :: Python :: 3.6
Classifier: Programming Language :: Python :: 3.7
Classifier: License :: OSI Approved :: MIT License
Classifier: Operating System :: OS Independent
Requires-Dist: dicttoxml (~=1.7.4)
Requires-Dist: lxml (~=4.2.5)
Requires-Dist: nested-lookup (~=0.1.5)
Requires-Dist: requests (~=2.18.4)
Requires-Dist: unittest-xml (~=0.2.2)
Requires-Dist: xmltodict (~=0.11.0)
Requires-Dist: six (~=1.11.0)
